pytest_historic/__init__.py
pytest_historic/app.py
pytest_historic/args.py
pytest_historic/templates/compare.html
pytest_historic/templates/dashboard.html
pytest_historic/templates/deldbconf.html
pytest_historic/templates/deleconf.html
pytest_historic/templates/ehistoric.html
pytest_historic/templates/eidtmetrics.html
pytest_historic/templates/failures.html
pytest_historic/templates/flaky.html
pytest_historic/templates/home.html
pytest_historic/templates/index.html
pytest_historic/templates/metrics.html
pytest_historic/templates/newdb.html
pytest_historic/templates/redirect.html
pytest_historic/templates/search.html
pytest_historic/templates/tmetrics.html
pytest_historic-0.1.2.dist-info/LICENSE
pytest_historic-0.1.2.dist-info/METADATA
pytest_historic-0.1.2.dist-info/WHEEL
pytest_historic-0.1.2.dist-info/entry_points.txt
pytest_historic-0.1.2.dist-info/top_level.txt
pytest_historic-0.1.2.dist-info/RECORD
